# Math

<!-- TOC -->

- [1. Arithmetic](#1-arithmetic)
  - [1.1. `1+2`](#11-12)
  - [1.2. add](#12-add)
  - [1.3. sub](#13-sub)
  - [1.4. mul](#14-mul)
  - [1.5. div](#15-div)
  - [1.6. rem](#16-rem)
  - [1.7. ineg](#17-ineg)
- [2. iinc](#2-iinc)
  - [2.1. int plus plus](#21-int-plus-plus)
  - [2.2. long plus plus](#22-long-plus-plus)
  - [2.3. float plus plus](#23-float-plus-plus)
  - [2.4. double plus plus](#24-double-plus-plus)
  - [2.5. Integer plus plus](#25-integer-plus-plus)
  - [2.6. i++ vs ++i](#26-i-vs-i)
- [3. Shift](#3-shift)
  - [3.1. shift left](#31-shift-left)
  - [3.2. arithmetic shift right](#32-arithmetic-shift-right)
  - [3.3. logical shift right](#33-logical-shift-right)
- [4. Logic](#4-logic)
  - [4.1. and](#41-and)
  - [4.2. or](#42-or)
  - [4.3. xor](#43-xor)
- [5. Summing-up](#5-summing-up)

<!-- /TOC -->

**Arithmetic and logic**. These instructions pop numeric values from the operand stack combine them and push the result on the stack. They do not have any argument. `xADD`, `xSUB`, `xMUL`, `xDIV` and `xREM` correspond to the `+`, `-`, `*`, `/` and `%` operations, where `x` is either `I`, `L`, `F` or `D`. Similarly there are other instructions corresponding to `<<`, `>>`, `>>>`, `|`, `&` and `^`, for `int` and `long` values.

## 1. Arithmetic

### 1.1. `1+2`

示例代码：

```java
public class HelloWorld {
    public void testSimple() {
        int a = 1 + 2;
    }
}
```

输出结果：

```txt
code='063CB1'
    0: iconst_3        // 06
    1: istore_1        // 3C
    2: return          // B1


LocalVariableTable:
index  start_pc  length  name_and_type
    0         0       3  this:Llsieun/sample/HelloWorld;
    1         2       1  a:I
```

```java
public class HelloWorld {
    public void testSimple() {
        int num = 128 + 256;
    }
}
```

```txt
=== === ===  === === ===  === === ===
HexCode: 1101803cb1
=== === ===  === === ===  === === ===
0000: sipush          384  // 110180
0003: istore_1             // 3c
0004: return               // b1
```

### 1.2. add

学习目标：

- `iadd`: Add `int`

示例代码：

```java
public class HelloWorld {
    public void testSimple() {
        int a = 1;
        int b = 2;
        int c = a + b;
    }
}
```

输出结果：

```txt
code='043C053D1B1C603EB1'
    0: iconst_1        // 04
    1: istore_1        // 3C
    2: iconst_2        // 05
    3: istore_2        // 3D
    4: iload_1         // 1B
    5: iload_2         // 1C
    6: iadd            // 60
    7: istore_3        // 3E
    8: return          // B1


LocalVariableTable:
index  start_pc  length  name_and_type
    0         0       9  this:Llsieun/sample/HelloWorld;
    1         2       7  a:I
    2         4       5  b:I
    3         8       1  c:I
```

### 1.3. sub

学习目标：

- `isub`: Subtract `int`

示例代码：

```java
public class HelloWorld {
    public void testSimple() {
        int a = 1;
        int b = 2;
        int c = a - b;
    }
}
```

输出结果：

```txt
code='043C053D1B1C643EB1'
    0: iconst_1        // 04
    1: istore_1        // 3C
    2: iconst_2        // 05
    3: istore_2        // 3D
    4: iload_1         // 1B
    5: iload_2         // 1C
    6: isub            // 64
    7: istore_3        // 3E
    8: return          // B1


LocalVariableTable:
index  start_pc  length  name_and_type
    0         0       9  this:Llsieun/sample/HelloWorld;
    1         2       7  a:I
    2         4       5  b:I
    3         8       1  c:I
```

### 1.4. mul

学习目标：

- `imul`: Multiply `int`

示例代码：

```java
public class HelloWorld {
    public void testSimple() {
        int a = 1;
        int b = 2;
        int c = a * b;
    }
}
```

输出结果：

```txt
code='043C053D1B1C683EB1'
    0: iconst_1        // 04
    1: istore_1        // 3C
    2: iconst_2        // 05
    3: istore_2        // 3D
    4: iload_1         // 1B
    5: iload_2         // 1C
    6: imul            // 68
    7: istore_3        // 3E
    8: return          // B1


LocalVariableTable:
index  start_pc  length  name_and_type
    0         0       9  this:Llsieun/sample/HelloWorld;
    1         2       7  a:I
    2         4       5  b:I
    3         8       1  c:I
```

### 1.5. div

学习目标：

- `idiv`: Divide `int`

示例代码：

```java
public class HelloWorld {
    public void testSimple() {
        int a = 1;
        int b = 2;
        int c = a / b;
    }
}
```

输出结果：

```txt
code='043C053D1B1C6C3EB1'
    0: iconst_1        // 04
    1: istore_1        // 3C
    2: iconst_2        // 05
    3: istore_2        // 3D
    4: iload_1         // 1B
    5: iload_2         // 1C
    6: idiv            // 6C
    7: istore_3        // 3E
    8: return          // B1


LocalVariableTable:
index  start_pc  length  name_and_type
    0         0       9  this:Llsieun/sample/HelloWorld;
    1         2       7  a:I
    2         4       5  b:I
    3         8       1  c:I
```

### 1.6. rem

学习目标：

- `irem`: Remainder `int`

示例代码：

```java
public class HelloWorld {
    public void testSimple() {
        int a = 1;
        int b = 2;
        int c = a % b;
    }
}
```

输出结果：

```txt
code='043C053D1B1C703EB1'
    0: iconst_1        // 04
    1: istore_1        // 3C
    2: iconst_2        // 05
    3: istore_2        // 3D
    4: iload_1         // 1B
    5: iload_2         // 1C
    6: irem            // 70
    7: istore_3        // 3E
    8: return          // B1


LocalVariableTable:
index  start_pc  length  name_and_type
    0         0       9  this:Llsieun/sample/HelloWorld;
    1         2       7  a:I
    2         4       5  b:I
    3         8       1  c:I
```

### 1.7. ineg

学习目标：

示例代码：

```java
public class HelloWorld {
    public void testSimple() {
        int a = 1;
        int b = -a;
    }
}
```

输出结果：

```txt
code='043C1B743DB1'
    0: iconst_1        // 04
    1: istore_1        // 3C
    2: iload_1         // 1B
    3: ineg            // 74
    4: istore_2        // 3D
    5: return          // B1


LocalVariableTable:
index  start_pc  length  name_and_type
    0         0       6  this:Llsieun/sample/HelloWorld;
    1         2       4  a:I
    2         5       1  b:I
```

## 2. iinc

学习目标：

- `iinc`

示例代码：

```java
public class HelloWorld {
    public void testSimple() {
        int i = 0;
        i++;
    }
}
```

输出结果：

```txt
code='033C840101B1'
    0: iconst_0        // 03
    1: istore_1        // 3C
    2: iinc 1 1        // 840101
    5: return          // B1


LocalVariableTable:
index  start_pc  length  name_and_type
    0         0       6  this:Llsieun/sample/HelloWorld;
    1         2       4  i:I
```

### 2.1. int plus plus

```java
public class HelloWorld {
    public void testSimple() {
        int num = 1;
        num++;
    }
}
```

```txt
=== === ===  === === ===  === === ===
HexCode: 043c840101b1
=== === ===  === === ===  === === ===
0000: iconst_1             // 04
0001: istore_1             // 3c
0002: iinc       1    1    // 840101
0005: return               // b1
```

### 2.2. long plus plus

```java
public class HelloWorld {
    public void testSimple() {
        long num = 1;
        num++;
    }
}
```

```txt
=== === ===  === === ===  === === ===
HexCode: 0a401f0a6140b1
=== === ===  === === ===  === === ===
0000: lconst_1             // 0a
0001: lstore_1             // 40
0002: lload_1              // 1f
0003: lconst_1             // 0a
0004: ladd                 // 61
0005: lstore_1             // 40
0006: return               // b1
```

### 2.3. float plus plus

```java
public class HelloWorld {
    public void testSimple() {
        float num = 1;
        num++;
    }
}
```

```txt
=== === ===  === === ===  === === ===
HexCode: 0c44230c6244b1
=== === ===  === === ===  === === ===
0000: fconst_1             // 0c
0001: fstore_1             // 44
0002: fload_1              // 23
0003: fconst_1             // 0c
0004: fadd                 // 62
0005: fstore_1             // 44
0006: return               // b1
```

### 2.4. double plus plus

```java
public class HelloWorld {
    public void testSimple() {
        double num = 1;
        num++;
    }
}
```

```txt
=== === ===  === === ===  === === ===
HexCode: 0f48270f6348b1
=== === ===  === === ===  === === ===
0000: dconst_1             // 0f
0001: dstore_1             // 48
0002: dload_1              // 27
0003: dconst_1             // 0f
0004: dadd                 // 63
0005: dstore_1             // 48
0006: return               // b1
```

### 2.5. Integer plus plus

```java
public class HelloWorld {
    public void testSimple() {
        Integer num = 1;
        num++;
    }
}
```

```txt
=== === ===  === === ===  === === ===
HexCode: 04b800024c2b4d2bb600030460b80002594c4e2c57b1
=== === ===  === === ===  === === ===
0000: iconst_1             // 04
0001: invokestatic    #2   // b80002     || java/lang/Integer.valueOf:(I)Ljava/lang/Integer;
0004: astore_1             // 4c
0005: aload_1              // 2b
0006: astore_2             // 4d
0007: aload_1              // 2b
0008: invokevirtual   #3   // b60003     || java/lang/Integer.intValue:()I
0011: iconst_1             // 04
0012: iadd                 // 60
0013: invokestatic    #2   // b80002     || java/lang/Integer.valueOf:(I)Ljava/lang/Integer;
0016: dup                  // 59
0017: astore_1             // 4c
0018: astore_3             // 4e
0019: aload_2              // 2c
0020: pop                  // 57
0021: return               // b1
```

### 2.6. i++ vs ++i

```java
public class HelloWorld {
    public void testSimple() {
        int num = 1;
        int result = num++;
    }
}
```

```txt
=== === ===  === === ===  === === ===
HexCode: 043c1b8401013db1
=== === ===  === === ===  === === ===
0000: iconst_1             // 04
0001: istore_1             // 3c
0002: iload_1              // 1b
0003: iinc       1    1    // 840101
0006: istore_2             // 3d
0007: return               // b1
```

```java
public class HelloWorld {
    public void testSimple() {
        int num = 1;
        int result = ++num;
    }
}
```

```txt
=== === ===  === === ===  === === ===
HexCode: 043c8401011b3db1
=== === ===  === === ===  === === ===
0000: iconst_1             // 04
0001: istore_1             // 3c
0002: iinc       1    1    // 840101
0005: iload_1              // 1b
0006: istore_2             // 3d
0007: return               // b1
```

## 3. Shift

### 3.1. shift left

学习目标：

- `ishl`: Shift left `int`

示例代码：

```java
public class HelloWorld {
    public void testSimple() {
        int a = 1;
        int b = 2;
        int c = a << b;
    }
}
```

输出结果：

```txt
code='043C053D1B1C783EB1'
    0: iconst_1        // 04
    1: istore_1        // 3C
    2: iconst_2        // 05
    3: istore_2        // 3D
    4: iload_1         // 1B
    5: iload_2         // 1C
    6: ishl            // 78
    7: istore_3        // 3E
    8: return          // B1


LocalVariableTable:
index  start_pc  length  name_and_type
    0         0       9  this:Llsieun/sample/HelloWorld;
    1         2       7  a:I
    2         4       5  b:I
    3         8       1  c:I
```

### 3.2. arithmetic shift right

学习目标：

- `ishr`: Arithmetic shift right `int`

示例代码：

```java
public class HelloWorld {
    public void testSimple() {
        int a = 1;
        int b = 2;
        int c = a >> b;
    }

    public static void main(String[] args) {
        int oldValue = -128;
        System.out.println(Integer.toBinaryString(oldValue));
        int newValue = oldValue >> 4;
        System.out.println(Integer.toBinaryString(newValue));
    }
}
```

输出结果（一）：

```txt
code='043C053D1B1C7A3EB1'
    0: iconst_1        // 04
    1: istore_1        // 3C
    2: iconst_2        // 05
    3: istore_2        // 3D
    4: iload_1         // 1B
    5: iload_2         // 1C
    6: ishr            // 7A
    7: istore_3        // 3E
    8: return          // B1


LocalVariableTable:
index  start_pc  length  name_and_type
    0         0       9  this:Llsieun/sample/HelloWorld;
    1         2       7  a:I
    2         4       5  b:I
    3         8       1  c:I
```

输出结果（二）：

```txt
11111111111111111111111110000000
11111111111111111111111111111000
```

### 3.3. logical shift right

学习目标：

- `iushr`: Logical shift right `int`

示例代码：

```java
public class HelloWorld {
    public void testSimple() {
        int a = 1;
        int b = 2;
        int c = a >>> b;
    }

    public static void main(String[] args) {
        int oldValue = -128;
        System.out.println(Integer.toBinaryString(oldValue));
        int newValue = oldValue >>> 4;
        System.out.println(Integer.toBinaryString(newValue));
    }
}
```

输出结果（一）：

```txt
code='043C053D1B1C7C3EB1'
    0: iconst_1        // 04
    1: istore_1        // 3C
    2: iconst_2        // 05
    3: istore_2        // 3D
    4: iload_1         // 1B
    5: iload_2         // 1C
    6: iushr           // 7C
    7: istore_3        // 3E
    8: return          // B1


LocalVariableTable:
index  start_pc  length  name_and_type
    0         0       9  this:Llsieun/sample/HelloWorld;
    1         2       7  a:I
    2         4       5  b:I
    3         8       1  c:I
```

输出结果（二）：

```txt
11111111111111111111111110000000
1111111111111111111111111000
```

## 4. Logic

### 4.1. and

学习目标：

- `iand`: Boolean AND `int`

示例代码：

```java
public class HelloWorld {
    public void testSimple() {
        int a = 1;
        int b = 2;
        int c = a & b;
    }
}
```

输出结果：

```txt
code='043C053D1B1C7E3EB1'
    0: iconst_1        // 04
    1: istore_1        // 3C
    2: iconst_2        // 05
    3: istore_2        // 3D
    4: iload_1         // 1B
    5: iload_2         // 1C
    6: iand            // 7E
    7: istore_3        // 3E
    8: return          // B1


LocalVariableTable:
index  start_pc  length  name_and_type
    0         0       9  this:Llsieun/sample/HelloWorld;
    1         2       7  a:I
    2         4       5  b:I
    3         8       1  c:I
```

### 4.2. or

学习目标：

- `ior`: Boolean OR `int`

示例代码：

```java
public class HelloWorld {
    public void testSimple() {
        int a = 1;
        int b = 2;
        int c = a | b;
    }
}
```

输出结果：

```txt
code='043C053D1B1C803EB1'
    0: iconst_1        // 04
    1: istore_1        // 3C
    2: iconst_2        // 05
    3: istore_2        // 3D
    4: iload_1         // 1B
    5: iload_2         // 1C
    6: ior             // 80
    7: istore_3        // 3E
    8: return          // B1


LocalVariableTable:
index  start_pc  length  name_and_type
    0         0       9  this:Llsieun/sample/HelloWorld;
    1         2       7  a:I
    2         4       5  b:I
    3         8       1  c:I
```



### 4.3. xor

学习目标：

- `ixor`: Boolean XOR `int`

示例代码：

```java
public class HelloWorld {
    public void testSimple() {
        int a = 1;
        int b = 2;
        int c = a ^ b;
    }
}
```

输出结果：

```txt
code='043C053D1B1C823EB1'
    0: iconst_1        // 04
    1: istore_1        // 3C
    2: iconst_2        // 05
    3: istore_2        // 3D
    4: iload_1         // 1B
    5: iload_2         // 1C
    6: ixor            // 82
    7: istore_3        // 3E
    8: return          // B1


LocalVariableTable:
index  start_pc  length  name_and_type
    0         0       9  this:Llsieun/sample/HelloWorld;
    1         2       7  a:I
    2         4       5  b:I
    3         8       1  c:I
```

学习目标：

示例代码：

```java
public class HelloWorld {
    public void testSimple() {
        int a = 0;
        int b = ~a;
    }
}
```

输出结果：

```txt
code='033c1b02823db1'
    0: iconst_0        // 03
    1: istore_1        // 3c
    2: iload_1         // 1b
    3: iconst_m1       // 02
    4: ixor            // 82
    5: istore_2        // 3d
    6: return          // b1


LocalVariableTable:
index  start_pc  length  name_and_type
    0         0       7  this:Llsieun/sample/HelloWorld;
    1         2       5  a:I
    2         6       1  b:I
```

## 5. Summing-up

知识总结

| opcode | mnemonic symbol | meaning                              |
| ------ | --------------- | ------------------------------------ |
| `96`   | `iadd`          | Add `int`                            |
| `97`   | `ladd`          |                                      |
| `98`   | `fadd`          |                                      |
| `99`   | `dadd`          |                                      |
| `100`  | `isub`          | Subtract `int`                       |
| `101`  | `lsub`          |                                      |
| `102`  | `fsub`          |                                      |
| `103`  | `dsub`          |                                      |
| `104`  | `imul`          | Multiply `int`                       |
| `105`  | `lmul`          |                                      |
| `106`  | `fmul`          |                                      |
| `107`  | `dmul`          |                                      |
| `108`  | `idiv`          | Divide `int`                         |
| `109`  | `ldiv`          |                                      |
| `110`  | `fdiv`          |                                      |
| `111`  | `ddiv`          |                                      |
| `112`  | `irem`          | Remainder `int`                      |
| `113`  | `lrem`          |                                      |
| `114`  | `frem`          |                                      |
| `115`  | `drem`          |                                      |
| `116`  | `ineg`          | Negate `int`                         |
| `117`  | `lneg`          |                                      |
| `118`  | `fneg`          |                                      |
| `119`  | `dneg`          |                                      |
| `120`  | `ishl`          | Shift left `int`                     |
| `121`  | `lshl`          |                                      |
| `122`  | `ishr`          | Arithmetic shift right `int`         |
| `123`  | `lshr`          |                                      |
| `124`  | `iushr`         | Logical shift right `int`            |
| `125`  | `lushr`         |                                      |
| `126`  | `iand`          | Boolean AND `int`                    |
| `127`  | `land`          |                                      |
| `128`  | `ior`           | Boolean OR `int`                     |
| `129`  | `lor`           |                                      |
| `130`  | `ixor`          | Boolean XOR `int`                    |
| `131`  | `lxor`          |                                      |
| `132`  | `iinc`          | Increment local variable by constant |

