# More Examples

## 变量

我好奇的地方在于：value是怎么赋值的，processNumber是如何调用的

```java
public class HelloWorld {
    public void testSimple() {
        int value = 0;
        processNumber(value = getNumber());
    }

    public int getNumber() {
        return 0;
    }

    public void processNumber(int num) {
        return;
    }
}
```

```txt
=== === ===  === === ===  === === ===
HexCode: 033c2a2ab60003593cb60004b1
=== === ===  === === ===  === === ===
0000: iconst_0             // 03
0001: istore_1             // 3c
0002: aload_0              // 2a
0003: aload_0              // 2a
0004: invokevirtual   #3   // b60003     || lsieun/sample/HelloWorld.getNumber:()I
0007: dup                  // 59
0008: istore_1             // 3c
0009: invokevirtual   #4   // b60004     || lsieun/sample/HelloWorld.processNumber:(I)V
0012: return               // b1
```
