-- dict_unit
INSERT INTO `dict_unit` (`id`, `name`) VALUES (1, 'u1');
INSERT INTO `dict_unit` (`id`, `name`) VALUES (2, 'u2');
INSERT INTO `dict_unit` (`id`, `name`) VALUES (4, 'u4');
INSERT INTO `dict_unit` (`id`, `name`) VALUES (8, 'u8');

-- dict_structure
INSERT INTO `dict_structure` (`name`) VALUES ('class_file');
INSERT INTO `dict_structure` (`name`) VALUES ('cp_info');
INSERT INTO `dict_structure` (`name`) VALUES ('field_info');
INSERT INTO `dict_structure` (`name`) VALUES ('method_info');
INSERT INTO `dict_structure` (`name`) VALUES ('attribute_info');

-- biz_opcode
INSERT INTO `biz_opcode` (`id`, `name`) VALUES (0, 'nop');
INSERT INTO `biz_opcode` (`id`, `name`) VALUES (1, 'aconst_null');
INSERT INTO `biz_opcode` (`id`, `name`) VALUES (2, 'iconst_m1');
INSERT INTO `biz_opcode` (`id`, `name`) VALUES (3, 'iconst_0');
INSERT INTO `biz_opcode` (`id`, `name`) VALUES (4, 'iconst_1');
INSERT INTO `biz_opcode` (`id`, `name`) VALUES (5, 'iconst_2');
INSERT INTO `biz_opcode` (`id`, `name`) VALUES (6, 'iconst_3');
INSERT INTO `biz_opcode` (`id`, `name`) VALUES (7, 'iconst_4');
INSERT INTO `biz_opcode` (`id`, `name`) VALUES (8, 'iconst_5');
INSERT INTO `biz_opcode` (`id`, `name`) VALUES (9, 'lconst_0');
INSERT INTO `biz_opcode` (`id`, `name`) VALUES (10, 'lconst_1');
INSERT INTO `biz_opcode` (`id`, `name`) VALUES (11, 'fconst_0');
INSERT INTO `biz_opcode` (`id`, `name`) VALUES (12, 'fconst_1');
INSERT INTO `biz_opcode` (`id`, `name`) VALUES (13, 'fconst_2');
INSERT INTO `biz_opcode` (`id`, `name`) VALUES (14, 'dconst_0');
INSERT INTO `biz_opcode` (`id`, `name`) VALUES (15, 'dconst_1');
INSERT INTO `biz_opcode` (`id`, `name`) VALUES (16, 'bipush');
INSERT INTO `biz_opcode` (`id`, `name`) VALUES (17, 'sipush');
INSERT INTO `biz_opcode` (`id`, `name`) VALUES (18, 'ldc');
INSERT INTO `biz_opcode` (`id`, `name`) VALUES (19, 'ldc_w');
INSERT INTO `biz_opcode` (`id`, `name`) VALUES (20, 'ldc2_w');
INSERT INTO `biz_opcode` (`id`, `name`) VALUES (21, 'iload');
INSERT INTO `biz_opcode` (`id`, `name`) VALUES (22, 'lload');
INSERT INTO `biz_opcode` (`id`, `name`) VALUES (23, 'fload');
INSERT INTO `biz_opcode` (`id`, `name`) VALUES (24, 'dload');
INSERT INTO `biz_opcode` (`id`, `name`) VALUES (25, 'aload');
INSERT INTO `biz_opcode` (`id`, `name`) VALUES (26, 'iload_0');
INSERT INTO `biz_opcode` (`id`, `name`) VALUES (27, 'iload_1');
INSERT INTO `biz_opcode` (`id`, `name`) VALUES (28, 'iload_2');
INSERT INTO `biz_opcode` (`id`, `name`) VALUES (29, 'iload_3');
INSERT INTO `biz_opcode` (`id`, `name`) VALUES (30, 'lload_0');
INSERT INTO `biz_opcode` (`id`, `name`) VALUES (31, 'lload_1');
INSERT INTO `biz_opcode` (`id`, `name`) VALUES (32, 'lload_2');
INSERT INTO `biz_opcode` (`id`, `name`) VALUES (33, 'lload_3');
INSERT INTO `biz_opcode` (`id`, `name`) VALUES (34, 'fload_0');
INSERT INTO `biz_opcode` (`id`, `name`) VALUES (35, 'fload_1');
INSERT INTO `biz_opcode` (`id`, `name`) VALUES (36, 'fload_2');
INSERT INTO `biz_opcode` (`id`, `name`) VALUES (37, 'fload_3');
INSERT INTO `biz_opcode` (`id`, `name`) VALUES (38, 'dload_0');
INSERT INTO `biz_opcode` (`id`, `name`) VALUES (39, 'dload_1');
INSERT INTO `biz_opcode` (`id`, `name`) VALUES (40, 'dload_2');
INSERT INTO `biz_opcode` (`id`, `name`) VALUES (41, 'dload_3');
INSERT INTO `biz_opcode` (`id`, `name`) VALUES (42, 'aload_0');
INSERT INTO `biz_opcode` (`id`, `name`) VALUES (43, 'aload_1');
INSERT INTO `biz_opcode` (`id`, `name`) VALUES (44, 'aload_2');
INSERT INTO `biz_opcode` (`id`, `name`) VALUES (45, 'aload_3');
INSERT INTO `biz_opcode` (`id`, `name`) VALUES (46, 'iaload');
INSERT INTO `biz_opcode` (`id`, `name`) VALUES (47, 'laload');
INSERT INTO `biz_opcode` (`id`, `name`) VALUES (48, 'faload');
INSERT INTO `biz_opcode` (`id`, `name`) VALUES (49, 'daload');
INSERT INTO `biz_opcode` (`id`, `name`) VALUES (50, 'aaload');
INSERT INTO `biz_opcode` (`id`, `name`) VALUES (51, 'baload');
INSERT INTO `biz_opcode` (`id`, `name`) VALUES (52, 'caload');
INSERT INTO `biz_opcode` (`id`, `name`) VALUES (53, 'saload');
INSERT INTO `biz_opcode` (`id`, `name`) VALUES (54, 'istore');
INSERT INTO `biz_opcode` (`id`, `name`) VALUES (55, 'lstore');
INSERT INTO `biz_opcode` (`id`, `name`) VALUES (56, 'fstore');
INSERT INTO `biz_opcode` (`id`, `name`) VALUES (57, 'dstore');
INSERT INTO `biz_opcode` (`id`, `name`) VALUES (58, 'astore');
INSERT INTO `biz_opcode` (`id`, `name`) VALUES (59, 'istore_0');
INSERT INTO `biz_opcode` (`id`, `name`) VALUES (60, 'istore_1');
INSERT INTO `biz_opcode` (`id`, `name`) VALUES (61, 'istore_2');
INSERT INTO `biz_opcode` (`id`, `name`) VALUES (62, 'istore_3');
INSERT INTO `biz_opcode` (`id`, `name`) VALUES (63, 'lstore_0');
INSERT INTO `biz_opcode` (`id`, `name`) VALUES (64, 'lstore_1');
INSERT INTO `biz_opcode` (`id`, `name`) VALUES (65, 'lstore_2');
INSERT INTO `biz_opcode` (`id`, `name`) VALUES (66, 'lstore_3');
INSERT INTO `biz_opcode` (`id`, `name`) VALUES (67, 'fstore_0');
INSERT INTO `biz_opcode` (`id`, `name`) VALUES (68, 'fstore_1');
INSERT INTO `biz_opcode` (`id`, `name`) VALUES (69, 'fstore_2');
INSERT INTO `biz_opcode` (`id`, `name`) VALUES (70, 'fstore_3');
INSERT INTO `biz_opcode` (`id`, `name`) VALUES (71, 'dstore_0');
INSERT INTO `biz_opcode` (`id`, `name`) VALUES (72, 'dstore_1');
INSERT INTO `biz_opcode` (`id`, `name`) VALUES (73, 'dstore_2');
INSERT INTO `biz_opcode` (`id`, `name`) VALUES (74, 'dstore_3');
INSERT INTO `biz_opcode` (`id`, `name`) VALUES (75, 'astore_0');
INSERT INTO `biz_opcode` (`id`, `name`) VALUES (76, 'astore_1');
INSERT INTO `biz_opcode` (`id`, `name`) VALUES (77, 'astore_2');
INSERT INTO `biz_opcode` (`id`, `name`) VALUES (78, 'astore_3');
INSERT INTO `biz_opcode` (`id`, `name`) VALUES (79, 'iastore');
INSERT INTO `biz_opcode` (`id`, `name`) VALUES (80, 'lastore');
INSERT INTO `biz_opcode` (`id`, `name`) VALUES (81, 'fastore');
INSERT INTO `biz_opcode` (`id`, `name`) VALUES (82, 'dastore');
INSERT INTO `biz_opcode` (`id`, `name`) VALUES (83, 'aastore');
INSERT INTO `biz_opcode` (`id`, `name`) VALUES (84, 'bastore');
INSERT INTO `biz_opcode` (`id`, `name`) VALUES (85, 'castore');
INSERT INTO `biz_opcode` (`id`, `name`) VALUES (86, 'sastore');
INSERT INTO `biz_opcode` (`id`, `name`) VALUES (87, 'pop');
INSERT INTO `biz_opcode` (`id`, `name`) VALUES (88, 'pop2');
INSERT INTO `biz_opcode` (`id`, `name`) VALUES (89, 'dup');
INSERT INTO `biz_opcode` (`id`, `name`) VALUES (90, 'dup_x1');
INSERT INTO `biz_opcode` (`id`, `name`) VALUES (91, 'dup_x2');
INSERT INTO `biz_opcode` (`id`, `name`) VALUES (92, 'dup2');
INSERT INTO `biz_opcode` (`id`, `name`) VALUES (93, 'dup2_x1');
INSERT INTO `biz_opcode` (`id`, `name`) VALUES (94, 'dup2_x2');
INSERT INTO `biz_opcode` (`id`, `name`) VALUES (95, 'swap');
INSERT INTO `biz_opcode` (`id`, `name`) VALUES (96, 'iadd');
INSERT INTO `biz_opcode` (`id`, `name`) VALUES (97, 'ladd');
INSERT INTO `biz_opcode` (`id`, `name`) VALUES (98, 'fadd');
INSERT INTO `biz_opcode` (`id`, `name`) VALUES (99, 'dadd');
INSERT INTO `biz_opcode` (`id`, `name`) VALUES (100, 'isub');
INSERT INTO `biz_opcode` (`id`, `name`) VALUES (101, 'lsub');
INSERT INTO `biz_opcode` (`id`, `name`) VALUES (102, 'fsub');
INSERT INTO `biz_opcode` (`id`, `name`) VALUES (103, 'dsub');
INSERT INTO `biz_opcode` (`id`, `name`) VALUES (104, 'imul');
INSERT INTO `biz_opcode` (`id`, `name`) VALUES (105, 'lmul');
INSERT INTO `biz_opcode` (`id`, `name`) VALUES (106, 'fmul');
INSERT INTO `biz_opcode` (`id`, `name`) VALUES (107, 'dmul');
INSERT INTO `biz_opcode` (`id`, `name`) VALUES (108, 'idiv');
INSERT INTO `biz_opcode` (`id`, `name`) VALUES (109, 'ldiv');
INSERT INTO `biz_opcode` (`id`, `name`) VALUES (110, 'fdiv');
INSERT INTO `biz_opcode` (`id`, `name`) VALUES (111, 'ddiv');
INSERT INTO `biz_opcode` (`id`, `name`) VALUES (112, 'irem');
INSERT INTO `biz_opcode` (`id`, `name`) VALUES (113, 'lrem');
INSERT INTO `biz_opcode` (`id`, `name`) VALUES (114, 'frem');
INSERT INTO `biz_opcode` (`id`, `name`) VALUES (115, 'drem');
INSERT INTO `biz_opcode` (`id`, `name`) VALUES (116, 'ineg');
INSERT INTO `biz_opcode` (`id`, `name`) VALUES (117, 'lneg');
INSERT INTO `biz_opcode` (`id`, `name`) VALUES (118, 'fneg');
INSERT INTO `biz_opcode` (`id`, `name`) VALUES (119, 'dneg');
INSERT INTO `biz_opcode` (`id`, `name`) VALUES (120, 'ishl');
INSERT INTO `biz_opcode` (`id`, `name`) VALUES (121, 'lshl');
INSERT INTO `biz_opcode` (`id`, `name`) VALUES (122, 'ishr');
INSERT INTO `biz_opcode` (`id`, `name`) VALUES (123, 'lshr');
INSERT INTO `biz_opcode` (`id`, `name`) VALUES (124, 'iushr');
INSERT INTO `biz_opcode` (`id`, `name`) VALUES (125, 'lushr');
INSERT INTO `biz_opcode` (`id`, `name`) VALUES (126, 'iand');
INSERT INTO `biz_opcode` (`id`, `name`) VALUES (127, 'land');
INSERT INTO `biz_opcode` (`id`, `name`) VALUES (128, 'ior');
INSERT INTO `biz_opcode` (`id`, `name`) VALUES (129, 'lor');
INSERT INTO `biz_opcode` (`id`, `name`) VALUES (130, 'ixor');
INSERT INTO `biz_opcode` (`id`, `name`) VALUES (131, 'lxor');
INSERT INTO `biz_opcode` (`id`, `name`) VALUES (132, 'iinc');
INSERT INTO `biz_opcode` (`id`, `name`) VALUES (133, 'i2l');
INSERT INTO `biz_opcode` (`id`, `name`) VALUES (134, 'i2f');
INSERT INTO `biz_opcode` (`id`, `name`) VALUES (135, 'i2d');
INSERT INTO `biz_opcode` (`id`, `name`) VALUES (136, 'l2i');
INSERT INTO `biz_opcode` (`id`, `name`) VALUES (137, 'l2f');
INSERT INTO `biz_opcode` (`id`, `name`) VALUES (138, 'l2d');
INSERT INTO `biz_opcode` (`id`, `name`) VALUES (139, 'f2i');
INSERT INTO `biz_opcode` (`id`, `name`) VALUES (140, 'f2l');
INSERT INTO `biz_opcode` (`id`, `name`) VALUES (141, 'f2d');
INSERT INTO `biz_opcode` (`id`, `name`) VALUES (142, 'd2i');
INSERT INTO `biz_opcode` (`id`, `name`) VALUES (143, 'd2l');
INSERT INTO `biz_opcode` (`id`, `name`) VALUES (144, 'd2f');
INSERT INTO `biz_opcode` (`id`, `name`) VALUES (145, 'i2b');
INSERT INTO `biz_opcode` (`id`, `name`) VALUES (146, 'i2c');
INSERT INTO `biz_opcode` (`id`, `name`) VALUES (147, 'i2s');
INSERT INTO `biz_opcode` (`id`, `name`) VALUES (148, 'lcmp');
INSERT INTO `biz_opcode` (`id`, `name`) VALUES (149, 'fcmpl');
INSERT INTO `biz_opcode` (`id`, `name`) VALUES (150, 'fcmpg');
INSERT INTO `biz_opcode` (`id`, `name`) VALUES (151, 'dcmpl');
INSERT INTO `biz_opcode` (`id`, `name`) VALUES (152, 'dcmpg');
INSERT INTO `biz_opcode` (`id`, `name`) VALUES (153, 'ifeq');
INSERT INTO `biz_opcode` (`id`, `name`) VALUES (154, 'ifne');
INSERT INTO `biz_opcode` (`id`, `name`) VALUES (155, 'iflt');
INSERT INTO `biz_opcode` (`id`, `name`) VALUES (156, 'ifge');
INSERT INTO `biz_opcode` (`id`, `name`) VALUES (157, 'ifgt');
INSERT INTO `biz_opcode` (`id`, `name`) VALUES (158, 'ifle');
INSERT INTO `biz_opcode` (`id`, `name`) VALUES (159, 'if_icmpeq');
INSERT INTO `biz_opcode` (`id`, `name`) VALUES (160, 'if_icmpne');
INSERT INTO `biz_opcode` (`id`, `name`) VALUES (161, 'if_icmplt');
INSERT INTO `biz_opcode` (`id`, `name`) VALUES (162, 'if_icmpge');
INSERT INTO `biz_opcode` (`id`, `name`) VALUES (163, 'if_icmpgt');
INSERT INTO `biz_opcode` (`id`, `name`) VALUES (164, 'if_icmple');
INSERT INTO `biz_opcode` (`id`, `name`) VALUES (165, 'if_acmpeq');
INSERT INTO `biz_opcode` (`id`, `name`) VALUES (166, 'if_acmpne');
INSERT INTO `biz_opcode` (`id`, `name`) VALUES (167, 'goto');
INSERT INTO `biz_opcode` (`id`, `name`) VALUES (168, 'jsr');
INSERT INTO `biz_opcode` (`id`, `name`) VALUES (169, 'ret');
INSERT INTO `biz_opcode` (`id`, `name`) VALUES (170, 'tableswitch');
INSERT INTO `biz_opcode` (`id`, `name`) VALUES (171, 'lookupswitch');
INSERT INTO `biz_opcode` (`id`, `name`) VALUES (172, 'ireturn');
INSERT INTO `biz_opcode` (`id`, `name`) VALUES (173, 'lreturn');
INSERT INTO `biz_opcode` (`id`, `name`) VALUES (174, 'freturn');
INSERT INTO `biz_opcode` (`id`, `name`) VALUES (175, 'dreturn');
INSERT INTO `biz_opcode` (`id`, `name`) VALUES (176, 'areturn');
INSERT INTO `biz_opcode` (`id`, `name`) VALUES (177, 'return');
INSERT INTO `biz_opcode` (`id`, `name`) VALUES (178, 'getstatic');
INSERT INTO `biz_opcode` (`id`, `name`) VALUES (179, 'putstatic');
INSERT INTO `biz_opcode` (`id`, `name`) VALUES (180, 'getfield');
INSERT INTO `biz_opcode` (`id`, `name`) VALUES (181, 'putfield');
INSERT INTO `biz_opcode` (`id`, `name`) VALUES (182, 'invokevirtual');
INSERT INTO `biz_opcode` (`id`, `name`) VALUES (183, 'invokespecial');
INSERT INTO `biz_opcode` (`id`, `name`) VALUES (184, 'invokestatic');
INSERT INTO `biz_opcode` (`id`, `name`) VALUES (185, 'invokeinterface');
INSERT INTO `biz_opcode` (`id`, `name`) VALUES (186, 'invokedynamic');
INSERT INTO `biz_opcode` (`id`, `name`) VALUES (187, 'new');
INSERT INTO `biz_opcode` (`id`, `name`) VALUES (188, 'newarray');
INSERT INTO `biz_opcode` (`id`, `name`) VALUES (189, 'anewarray');
INSERT INTO `biz_opcode` (`id`, `name`) VALUES (190, 'arraylength');
INSERT INTO `biz_opcode` (`id`, `name`) VALUES (191, 'athrow');
INSERT INTO `biz_opcode` (`id`, `name`) VALUES (192, 'checkcast');
INSERT INTO `biz_opcode` (`id`, `name`) VALUES (193, 'instanceof');
INSERT INTO `biz_opcode` (`id`, `name`) VALUES (194, 'monitorenter');
INSERT INTO `biz_opcode` (`id`, `name`) VALUES (195, 'monitorexit');
INSERT INTO `biz_opcode` (`id`, `name`) VALUES (196, 'wide');
INSERT INTO `biz_opcode` (`id`, `name`) VALUES (197, 'multianewarray');
INSERT INTO `biz_opcode` (`id`, `name`) VALUES (198, 'ifnull');
INSERT INTO `biz_opcode` (`id`, `name`) VALUES (199, 'ifnonnull');
INSERT INTO `biz_opcode` (`id`, `name`) VALUES (200, 'goto_w');
INSERT INTO `biz_opcode` (`id`, `name`) VALUES (201, 'jsr_w');
INSERT INTO `biz_opcode` (`id`, `name`) VALUES (202, 'breakpoint');
INSERT INTO `biz_opcode` (`id`, `name`) VALUES (254, 'impdep1');
INSERT INTO `biz_opcode` (`id`, `name`) VALUES (255, 'impdep2');

